certdeploy/__init__.py
certdeploy/errors.py
certdeploy/client/__init__.py
certdeploy/client/_main.py
certdeploy/client/daemon.py
certdeploy/client/deploy.py
certdeploy/client/errors.py
certdeploy/client/update.py
certdeploy/client/config/__init__.py
certdeploy/client/config/client.py
certdeploy/client/config/service.py
certdeploy/server/__init__.py
certdeploy/server/_main.py
certdeploy/server/renew.py
certdeploy/server/server.py
certdeploy/server/config/__init__.py
certdeploy/server/config/_validation.py
certdeploy/server/config/client.py
certdeploy/server/config/server.py
certdeploy-0.5.3.dist-info/licenses/LICENSE.txt
certdeploy-0.5.3.dist-info/METADATA
certdeploy-0.5.3.dist-info/WHEEL
certdeploy-0.5.3.dist-info/entry_points.txt
certdeploy-0.5.3.dist-info/top_level.txt
certdeploy-0.5.3.dist-info/RECORD
