Metadata-Version: 2.4
Name: certdeploy
Version: 0.5.3
Summary: A tool to automatically sync certificates and update services.
Home-page: https://github.com/haxwithaxe/certdeploy/
Author: haxwithaxe
Author-email: spam@haxwithaxe.net
License: GPL-3.0-only
Project-URL: Documentation, https://certdeploy.readthedocs.org/
Project-URL: Source, https://github.com/haxwithaxe/certdeploy/
Project-URL: Tracker, https://github.com/haxwithaxe/certdeploy/issues
Project-URL: Download, https://pypi.org/project/certdeploy/#files
Platform: any
Classifier: Development Status :: 3 - Alpha
Classifier: Programming Language :: Python
Classifier: Environment :: No Input/Output (Daemon)
Classifier: Topic :: System :: Systems Administration
Classifier: Topic :: Utilities
Requires-Python: >=3.8
License-File: LICENSE.txt
Requires-Dist: docker==7.1.0
Requires-Dist: paramiko==4.0.0
Requires-Dist: PyYAML==6.0.2
Requires-Dist: schedule==1.2.2
Requires-Dist: typer==0.16.0
Provides-Extra: docs
Requires-Dist: sphinx; extra == "docs"
Requires-Dist: myst-parser; extra == "docs"
Provides-Extra: testing
Requires-Dist: setuptools; extra == "testing"
Requires-Dist: pytest; extra == "testing"
Requires-Dist: pytest-cov; extra == "testing"
Dynamic: license-file
